lmpack/__init__.py
lmpack/dir_tree.py
lmpack/formatting.py
lmpack/ignores.py
lmpack/lm_packer.py
lmpack/main.py
lmpack/nodes.py
lmpack/tokenizers.py
lmpack-1.3.0.dist-info/METADATA
lmpack-1.3.0.dist-info/WHEEL
lmpack-1.3.0.dist-info/entry_points.txt
lmpack-1.3.0.dist-info/licenses/LICENSE
lmpack-1.3.0.dist-info/RECORD
