Metadata-Version: 2.4
Name: lmpack
Version: 1.3.0
Summary: Intelligently pack project context for LLMs, respecting .gitignore, skipping noise, and counting tokens.
License: MIT
License-File: LICENSE
Keywords: llm,context,prompt,packaging,ai,developer-tools,cli,git,gitignore,tiktoken,openai,gemini,llama,anthropic,claude,code-analysis
Author: Ionite
Author-email: dev@ionite.io
Requires-Python: >=3.10,<3.15
Classifier: Development Status :: 4 - Beta
Classifier: Environment :: Console
Classifier: Intended Audience :: Developers
Classifier: License :: OSI Approved :: MIT License
Classifier: Operating System :: OS Independent
Classifier: Programming Language :: Python :: 3
Classifier: Programming Language :: Python :: 3.10
Classifier: Programming Language :: Python :: 3.11
Classifier: Programming Language :: Python :: 3.12
Classifier: Programming Language :: Python :: 3.13
Classifier: Programming Language :: Python :: 3.14
Classifier: Programming Language :: Python :: 3 :: Only
Classifier: Topic :: Software Development :: Build Tools
Classifier: Topic :: Software Development :: Libraries :: Python Modules
Classifier: Topic :: Text Processing
Classifier: Topic :: Text Processing :: Filters
Classifier: Topic :: Utilities
Classifier: Typing :: Typed
Provides-Extra: all
Provides-Extra: tiktoken
Provides-Extra: tokenization
Provides-Extra: vertexai
Requires-Dist: google-cloud-aiplatform[tokenization] (>=1.87.0,<2.0.0) ; extra == "vertexai" or extra == "tokenization" or extra == "all"
Requires-Dist: py-walk (>=0.3.3)
Requires-Dist: rich (>=13.7.1)
Requires-Dist: tiktoken (>=0.9.0) ; extra == "tiktoken" or extra == "tokenization" or extra == "all"
Requires-Dist: typer (>=0.15.2,<0.16.0)
Project-URL: Documentation, https://github.com/ionite34/lmpack/blob/main/README.md
Project-URL: Homepage, https://github.com/ionite34/lmpack
Project-URL: Repository, https://github.com/ionite34/lmpack
